{
  "message": "success",
  "status": 200,
  "data": {
    "total": 31,
    "items": [
      {
        "type": "Add",
        "pairToken": {
          "address": "0xeC8c20660984962Ada1E2bEF07A4A273dcDdAf30",
          "name": "WXCFX&USDC LP",
          "symbol": "WXCFX&USDC LP",
          "decimals": 18,
          "icon": "",
          "amount": "0",
          "totalPrice": 0
        },
        "tokenA": {
          "address": "0x653d07E59d7FEb93F0c0199a12dA6730845D6a68",
          "name": "USDC",
          "symbol": "USDC",
          "decimals": 18,
          "icon": "http://testapi.artixv.com/coin/usdc-logo.png",
          "amount": "2000000000000000000000",
          "totalPrice": 0
        },
        "tokenB": {
          "address": "0x16C2473A9957d00B832C27cFa34773721f47992e",
          "name": "WXCFX",
          "symbol": "WXCFX",
          "decimals": 18,
          "icon": "http://testapi.artixv.com/coin/wxCFX-logo.png",
          "amount": "10000000000000000000000",
          "totalPrice": 0
        },
        "time": "1720607198"
      },
      {
        "type": "Swap",
        "pay": {
          "token": {
            "address": "0x7CBf5971d740b9f8eB957D8b3a07617fCd2AF36E",
            "name": "BTC",
            "symbol": "BTC",
            "decimals": 18,
            "icon": "http://testapi.artixv.com/coin/bitcoin-logo.png"
          },
          "amount": "10000000000"
        },
        "received": {
          "token": {
            "address": "0x84A1894b366a2346D92a7a57D4150Ee08aaf3423",
            "name": "SLC",
            "symbol": "SLC",
            "decimals": 18,
            "icon": "http://testapi.artixv.com/coin/bitcoin-logo.png"
          },
          "amount": "388862877799558"
        },
        "time": "1720281195"
      },
      {
        "type": "Swap",
        "pay": {
          "token": {
            "address": "0x84A1894b366a2346D92a7a57D4150Ee08aaf3423",
            "name": "SLC",
            "symbol": "SLC",
            "decimals": 18,
            "icon": "http://testapi.artixv.com/coin/SLC-logo.png"
          },
          "amount": "1000000000000000000"
        },
        "received": {
          "token": {
            "address": "0x4a64578C034bbb338b4A78151F5e26A85D6ABeD6",
            "name": "USDT",
            "symbol": "USDT",
            "decimals": 18,
            "icon": "http://testapi.artixv.com/coin/SLC-logo.png"
          },
          "amount": "951160880548615693"
        },
        "time": "1720245350"
      },
      {
        "type": "Add",
        "pairToken": {
          "address": "0x9Fc50bf0F2E6c0737288eDe070820DB0DcC384A9",
          "name": "BTC&WXCFX LP",
          "symbol": "BTC&WXCFX LP",
          "decimals": 18,
          "icon": "",
          "amount": "2287808120312622730019",
          "totalPrice": 0
        },
        "tokenA": {
          "address": "0x7CBf5971d740b9f8eB957D8b3a07617fCd2AF36E",
          "name": "BTC",
          "symbol": "BTC",
          "decimals": 18,
          "icon": "http://testapi.artixv.com/coin/bitcoin-logo.png",
          "amount": "57673263892536572",
          "totalPrice": 0
        },
        "tokenB": {
          "address": "0x16C2473A9957d00B832C27cFa34773721f47992e",
          "name": "WXCFX",
          "symbol": "WXCFX",
          "decimals": 18,
          "icon": "http://testapi.artixv.com/coin/wxCFX-logo.png",
          "amount": "10000000000000000000000",
          "totalPrice": 0
        },
        "time": "1720193905"
      },
      {
        "type": "Add",
        "pairToken": {
          "address": "0x9Fc50bf0F2E6c0737288eDe070820DB0DcC384A9",
          "name": "BTC&WXCFX LP",
          "symbol": "BTC&WXCFX LP",
          "decimals": 18,
          "icon": "",
          "amount": "0",
          "totalPrice": 0
        },
        "tokenA": {
          "address": "0x7CBf5971d740b9f8eB957D8b3a07617fCd2AF36E",
          "name": "BTC",
          "symbol": "BTC",
          "decimals": 18,
          "icon": "http://testapi.artixv.com/coin/bitcoin-logo.png",
          "amount": "57673263892536572",
          "totalPrice": 0
        },
        "tokenB": {
          "address": "0x16C2473A9957d00B832C27cFa34773721f47992e",
          "name": "WXCFX",
          "symbol": "WXCFX",
          "decimals": 18,
          "icon": "http://testapi.artixv.com/coin/wxCFX-logo.png",
          "amount": "10000000000000000000000",
          "totalPrice": 0
        },
        "time": "1720193763"
      },
      {
        "type": "Add",
        "pairToken": {
          "address": "0x453f3dcE4Ae790d45e1B660bE384Cf77C12E14F3",
          "name": "WXCFX&SLC LP",
          "symbol": "WXCFX&SLC LP",
          "decimals": 18,
          "icon": "",
          "amount": "239368165442083001",
          "totalPrice": 0
        },
        "tokenA": {
          "address": "0x84A1894b366a2346D92a7a57D4150Ee08aaf3423",
          "name": "SLC",
          "symbol": "SLC",
          "decimals": 18,
          "icon": "http://testapi.artixv.com/coin/SLC-logo.png",
          "amount": "229200000000000000",
          "totalPrice": 0
        },
        "tokenB": {
          "address": "0x16C2473A9957d00B832C27cFa34773721f47992e",
          "name": "WXCFX",
          "symbol": "WXCFX",
          "decimals": 18,
          "icon": "http://testapi.artixv.com/coin/wxCFX-logo.png",
          "amount": "1000000000000000000",
          "totalPrice": 0
        },
        "time": "1720155969"
      },
      {
        "type": "Swap",
        "pay": {
          "token": {
            "address": "0x84A1894b366a2346D92a7a57D4150Ee08aaf3423",
            "name": "SLC",
            "symbol": "SLC",
            "decimals": 18,
            "icon": "http://testapi.artixv.com/coin/SLC-logo.png"
          },
          "amount": "2000000000000000000"
        },
        "received": {
          "token": {
            "address": "0x7CBf5971d740b9f8eB957D8b3a07617fCd2AF36E",
            "name": "BTC",
            "symbol": "BTC",
            "decimals": 18,
            "icon": "http://testapi.artixv.com/coin/SLC-logo.png"
          },
          "amount": "50369756668480"
        },
        "time": "1720150088"
      },
      {
        "type": "Swap",
        "pay": {
          "token": {
            "address": "0x84A1894b366a2346D92a7a57D4150Ee08aaf3423",
            "name": "SLC",
            "symbol": "SLC",
            "decimals": 18,
            "icon": "http://testapi.artixv.com/coin/SLC-logo.png"
          },
          "amount": "2000000000000000000"
        },
        "received": {
          "token": {
            "address": "0x7CBf5971d740b9f8eB957D8b3a07617fCd2AF36E",
            "name": "BTC",
            "symbol": "BTC",
            "decimals": 18,
            "icon": "http://testapi.artixv.com/coin/SLC-logo.png"
          },
          "amount": "50374267657863"
        },
        "time": "1720149992"
      },
      {
        "type": "Swap",
        "pay": {
          "token": {
            "address": "0x84A1894b366a2346D92a7a57D4150Ee08aaf3423",
            "name": "SLC",
            "symbol": "SLC",
            "decimals": 18,
            "icon": "http://testapi.artixv.com/coin/SLC-logo.png"
          },
          "amount": "2000000000000000000"
        },
        "received": {
          "token": {
            "address": "0x16C2473A9957d00B832C27cFa34773721f47992e",
            "name": "WXCFX",
            "symbol": "WXCFX",
            "decimals": 18,
            "icon": "http://testapi.artixv.com/coin/SLC-logo.png"
          },
          "amount": "8749503024603379773"
        },
        "time": "1720148665"
      },
      {
        "type": "Swap",
        "pay": {
          "token": {
            "address": "0x16C2473A9957d00B832C27cFa34773721f47992e",
            "name": "WXCFX",
            "symbol": "WXCFX",
            "decimals": 18,
            "icon": "http://testapi.artixv.com/coin/wxCFX-logo.png"
          },
          "amount": "2000000000000000000"
        },
        "received": {
          "token": {
            "address": "0x84A1894b366a2346D92a7a57D4150Ee08aaf3423",
            "name": "SLC",
            "symbol": "SLC",
            "decimals": 18,
            "icon": "http://testapi.artixv.com/coin/wxCFX-logo.png"
          },
          "amount": "456437835212489598"
        },
        "time": "1720148499"
      },
      {
        "type": "Add",
        "pairToken": {
          "address": "0x453f3dcE4Ae790d45e1B660bE384Cf77C12E14F3",
          "name": "WXCFX&SLC LP",
          "symbol": "WXCFX&SLC LP",
          "decimals": 18,
          "icon": "",
          "amount": "382441421222980627",
          "totalPrice": 0
        },
        "tokenA": {
          "address": "0x84A1894b366a2346D92a7a57D4150Ee08aaf3423",
          "name": "SLC",
          "symbol": "SLC",
          "decimals": 18,
          "icon": "http://testapi.artixv.com/coin/SLC-logo.png",
          "amount": "365671055228312577",
          "totalPrice": 0
        },
        "tokenB": {
          "address": "0x16C2473A9957d00B832C27cFa34773721f47992e",
          "name": "WXCFX",
          "symbol": "WXCFX",
          "decimals": 18,
          "icon": "http://testapi.artixv.com/coin/wxCFX-logo.png",
          "amount": "1600000000000000000",
          "totalPrice": 0
        },
        "time": "1720148001"
      },
      {
        "type": "Remove",
        "pairToken": {
          "address": "0x453f3dcE4Ae790d45e1B660bE384Cf77C12E14F3",
          "name": "WXCFX&SLC LP",
          "symbol": "WXCFX&SLC LP",
          "decimals": 18,
          "icon": "",
          "amount": "101000000000000000",
          "totalPrice": 0
        },
        "tokenA": {
          "address": "0x84A1894b366a2346D92a7a57D4150Ee08aaf3423",
          "name": "SLC",
          "symbol": "SLC",
          "decimals": 18,
          "icon": "http://testapi.artixv.com/coin/SLC-logo.png",
          "amount": "96571068217336457",
          "totalPrice": 0
        },
        "tokenB": {
          "address": "0x16C2473A9957d00B832C27cFa34773721f47992e",
          "name": "WXCFX",
          "symbol": "WXCFX",
          "decimals": 18,
          "icon": "http://testapi.artixv.com/coin/wxCFX-logo.png",
          "amount": "422548372200980549",
          "totalPrice": 0
        },
        "time": "1720147848"
      },
      {
        "type": "Remove",
        "pairToken": {
          "address": "0x453f3dcE4Ae790d45e1B660bE384Cf77C12E14F3",
          "name": "WXCFX&SLC LP",
          "symbol": "WXCFX&SLC LP",
          "decimals": 18,
          "icon": "",
          "amount": "123000000000000000",
          "totalPrice": 0
        },
        "tokenA": {
          "address": "0x84A1894b366a2346D92a7a57D4150Ee08aaf3423",
          "name": "SLC",
          "symbol": "SLC",
          "decimals": 18,
          "icon": "http://testapi.artixv.com/coin/SLC-logo.png",
          "amount": "117606350403290932",
          "totalPrice": 0
        },
        "tokenB": {
          "address": "0x16C2473A9957d00B832C27cFa34773721f47992e",
          "name": "WXCFX",
          "symbol": "WXCFX",
          "decimals": 18,
          "icon": "http://testapi.artixv.com/coin/wxCFX-logo.png",
          "amount": "514588611690303044",
          "totalPrice": 0
        },
        "time": "1720106486"
      },
      {
        "type": "Remove",
        "pairToken": {
          "address": "0x391CB85Bb82059C0B3bEaf2B3BaD2b9A21E43F23",
          "name": "USDC&SLC LP",
          "symbol": "USDC&SLC LP",
          "decimals": 18,
          "icon": "",
          "amount": "1100000000000000000",
          "totalPrice": 0
        },
        "tokenA": {
          "address": "0x84A1894b366a2346D92a7a57D4150Ee08aaf3423",
          "name": "SLC",
          "symbol": "SLC",
          "decimals": 18,
          "icon": "http://testapi.artixv.com/coin/SLC-logo.png",
          "amount": "1123205579361130285",
          "totalPrice": 0
        },
        "tokenB": {
          "address": "0x653d07E59d7FEb93F0c0199a12dA6730845D6a68",
          "name": "USDC",
          "symbol": "USDC",
          "decimals": 18,
          "icon": "http://testapi.artixv.com/coin/usdc-logo.png",
          "amount": "1077274320356118347",
          "totalPrice": 0
        },
        "time": "1720100887"
      },
      {
        "type": "Remove",
        "pairToken": {
          "address": "0x453f3dcE4Ae790d45e1B660bE384Cf77C12E14F3",
          "name": "WXCFX&SLC LP",
          "symbol": "WXCFX&SLC LP",
          "decimals": 18,
          "icon": "",
          "amount": "100000000000",
          "totalPrice": 0
        },
        "tokenA": {
          "address": "0x84A1894b366a2346D92a7a57D4150Ee08aaf3423",
          "name": "SLC",
          "symbol": "SLC",
          "decimals": 18,
          "icon": "http://testapi.artixv.com/coin/SLC-logo.png",
          "amount": "95614919027",
          "totalPrice": 0
        },
        "tokenB": {
          "address": "0x16C2473A9957d00B832C27cFa34773721f47992e",
          "name": "WXCFX",
          "symbol": "WXCFX",
          "decimals": 18,
          "icon": "http://testapi.artixv.com/coin/wxCFX-logo.png",
          "amount": "418364724951",
          "totalPrice": 0
        },
        "time": "1720092737"
      },
      {
        "type": "Add",
        "pairToken": {
          "address": "0x391CB85Bb82059C0B3bEaf2B3BaD2b9A21E43F23",
          "name": "USDC&SLC LP",
          "symbol": "USDC&SLC LP",
          "decimals": 18,
          "icon": "",
          "amount": "979339864591547497",
          "totalPrice": 0
        },
        "tokenA": {
          "address": "0x84A1894b366a2346D92a7a57D4150Ee08aaf3423",
          "name": "SLC",
          "symbol": "SLC",
          "decimals": 18,
          "icon": "http://testapi.artixv.com/coin/SLC-logo.png",
          "amount": "1000000000000000000",
          "totalPrice": 0
        },
        "tokenB": {
          "address": "0x653d07E59d7FEb93F0c0199a12dA6730845D6a68",
          "name": "USDC",
          "symbol": "USDC",
          "decimals": 18,
          "icon": "http://testapi.artixv.com/coin/usdc-logo.png",
          "amount": "959106988205011184",
          "totalPrice": 0
        },
        "time": "1720096302"
      },
      {
        "type": "Add",
        "pairToken": null,
        "tokenA": {
          "address": "0x16C2473A9957d00B832C27cFa34773721f47992e",
          "name": "WXCFX",
          "symbol": "WXCFX",
          "decimals": 18,
          "icon": "http://testapi.artixv.com/coin/wxCFX-logo.png",
          "amount": "500000000000000000000",
          "totalPrice": 0
        },
        "tokenB": null,
        "time": "1720092060"
      },
      {
        "type": "Add",
        "pairToken": {
          "address": "0x453f3dcE4Ae790d45e1B660bE384Cf77C12E14F3",
          "name": "WXCFX&SLC LP",
          "symbol": "WXCFX&SLC LP",
          "decimals": 18,
          "icon": "",
          "amount": "1197976729924620855",
          "totalPrice": 0
        },
        "tokenA": {
          "address": "0x84A1894b366a2346D92a7a57D4150Ee08aaf3423",
          "name": "SLC",
          "symbol": "SLC",
          "decimals": 18,
          "icon": "http://testapi.artixv.com/coin/SLC-logo.png",
          "amount": "1148170663510512855",
          "totalPrice": 0
        },
        "tokenB": {
          "address": "0x16C2473A9957d00B832C27cFa34773721f47992e",
          "name": "WXCFX",
          "symbol": "WXCFX",
          "decimals": 18,
          "icon": "http://testapi.artixv.com/coin/wxCFX-logo.png",
          "amount": "5000000000000000000",
          "totalPrice": 0
        },
        "time": "1720005622"
      },
      {
        "type": "Add",
        "pairToken": {
          "address": "0x391CB85Bb82059C0B3bEaf2B3BaD2b9A21E43F23",
          "name": "USDC&SLC LP",
          "symbol": "USDC&SLC LP",
          "decimals": 18,
          "icon": "",
          "amount": "14690097968873212277",
          "totalPrice": 0
        },
        "tokenA": {
          "address": "0x84A1894b366a2346D92a7a57D4150Ee08aaf3423",
          "name": "SLC",
          "symbol": "SLC",
          "decimals": 18,
          "icon": "http://testapi.artixv.com/coin/SLC-logo.png",
          "amount": "15000000000000000000",
          "totalPrice": 0
        },
        "tokenB": {
          "address": "0x653d07E59d7FEb93F0c0199a12dA6730845D6a68",
          "name": "USDC",
          "symbol": "USDC",
          "decimals": 18,
          "icon": "http://testapi.artixv.com/coin/usdc-logo.png",
          "amount": "14386604823075167573",
          "totalPrice": 0
        },
        "time": "1720004045"
      },
      {
        "type": "Add",
        "pairToken": {
          "address": "0x453f3dcE4Ae790d45e1B660bE384Cf77C12E14F3",
          "name": "WXCFX&SLC LP",
          "symbol": "WXCFX&SLC LP",
          "decimals": 18,
          "icon": "",
          "amount": "1147716489191606274",
          "totalPrice": 0
        },
        "tokenA": {
          "address": "0x84A1894b366a2346D92a7a57D4150Ee08aaf3423",
          "name": "SLC",
          "symbol": "SLC",
          "decimals": 18,
          "icon": "http://testapi.artixv.com/coin/SLC-logo.png",
          "amount": "1100000000000000000",
          "totalPrice": 0
        },
        "tokenB": {
          "address": "0x16C2473A9957d00B832C27cFa34773721f47992e",
          "name": "WXCFX",
          "symbol": "WXCFX",
          "decimals": 18,
          "icon": "http://testapi.artixv.com/coin/wxCFX-logo.png",
          "amount": "5000000000000000000",
          "totalPrice": 0
        },
        "time": "1720003856"
      },
      {
        "type": "Add",
        "pairToken": {
          "address": "0x453f3dcE4Ae790d45e1B660bE384Cf77C12E14F3",
          "name": "WXCFX&SLC LP",
          "symbol": "WXCFX&SLC LP",
          "decimals": 18,
          "icon": "",
          "amount": "1197976729924620855",
          "totalPrice": 0
        },
        "tokenA": {
          "address": "0x84A1894b366a2346D92a7a57D4150Ee08aaf3423",
          "name": "SLC",
          "symbol": "SLC",
          "decimals": 18,
          "icon": "http://testapi.artixv.com/coin/SLC-logo.png",
          "amount": "1148170663510512881",
          "totalPrice": 0
        },
        "tokenB": {
          "address": "0x16C2473A9957d00B832C27cFa34773721f47992e",
          "name": "WXCFX",
          "symbol": "WXCFX",
          "decimals": 18,
          "icon": "http://testapi.artixv.com/coin/wxCFX-logo.png",
          "amount": "5000000000000000000",
          "totalPrice": 0
        },
        "time": "1720003443"
      },
      {
        "type": "Swap",
        "pay": {
          "token": {
            "address": "0x7CBf5971d740b9f8eB957D8b3a07617fCd2AF36E",
            "name": "BTC",
            "symbol": "BTC",
            "decimals": 18,
            "icon": "http://testapi.artixv.com/coin/bitcoin-logo.png"
          },
          "amount": "1000000000000000"
        },
        "received": {
          "token": {
            "address": "0x7CBf5971d740b9f8eB957D8b3a07617fCd2AF36E",
            "name": "BTC",
            "symbol": "BTC",
            "decimals": 18,
            "icon": "http://testapi.artixv.com/coin/bitcoin-logo.png"
          },
          "amount": "997536285356950"
        },
        "time": "1719938466"
      },
      {
        "type": "Swap",
        "pay": {
          "token": {
            "address": "0x7CBf5971d740b9f8eB957D8b3a07617fCd2AF36E",
            "name": "BTC",
            "symbol": "BTC",
            "decimals": 18,
            "icon": "http://testapi.artixv.com/coin/bitcoin-logo.png"
          },
          "amount": "1000000000000000"
        },
        "received": {
          "token": {
            "address": "0x653d07E59d7FEb93F0c0199a12dA6730845D6a68",
            "name": "USDC",
            "symbol": "USDC",
            "decimals": 18,
            "icon": "http://testapi.artixv.com/coin/bitcoin-logo.png"
          },
          "amount": "38771261564219189338"
        },
        "time": "1719938383"
      },
      {
        "type": "Add",
        "pairToken": null,
        "tokenA": {
          "address": "0x16C2473A9957d00B832C27cFa34773721f47992e",
          "name": "WXCFX",
          "symbol": "WXCFX",
          "decimals": 18,
          "icon": "http://testapi.artixv.com/coin/wxCFX-logo.png",
          "amount": "1000000000000000000",
          "totalPrice": 0
        },
        "tokenB": null,
        "time": "1719934510"
      },
      {
        "type": "Swap",
        "pay": {
          "token": {
            "address": "0x16C2473A9957d00B832C27cFa34773721f47992e",
            "name": "WXCFX",
            "symbol": "WXCFX",
            "decimals": 18,
            "icon": "http://testapi.artixv.com/coin/wxCFX-logo.png"
          },
          "amount": "6000000000000000000"
        },
        "received": {
          "token": {
            "address": "0x653d07E59d7FEb93F0c0199a12dA6730845D6a68",
            "name": "USDC",
            "symbol": "USDC",
            "decimals": 18,
            "icon": "http://testapi.artixv.com/coin/wxCFX-logo.png"
          },
          "amount": "1376502646700226149"
        },
        "time": "1719916092"
      },
      {
        "type": "Swap",
        "pay": {
          "token": {
            "address": "0x16C2473A9957d00B832C27cFa34773721f47992e",
            "name": "WXCFX",
            "symbol": "WXCFX",
            "decimals": 18,
            "icon": "http://testapi.artixv.com/coin/wxCFX-logo.png"
          },
          "amount": "5000000000000000000"
        },
        "received": {
          "token": {
            "address": "0x653d07E59d7FEb93F0c0199a12dA6730845D6a68",
            "name": "USDC",
            "symbol": "USDC",
            "decimals": 18,
            "icon": "http://testapi.artixv.com/coin/wxCFX-logo.png"
          },
          "amount": "1151569399343369029"
        },
        "time": "1719903986"
      },
      {
        "type": "Add",
        "pairToken": {
          "address": "0x391CB85Bb82059C0B3bEaf2B3BaD2b9A21E43F23",
          "name": "USDC&SLC LP",
          "symbol": "USDC&SLC LP",
          "decimals": 18,
          "icon": "",
          "amount": "1000000000000000000000",
          "totalPrice": 0
        },
        "tokenA": {
          "address": "0x84A1894b366a2346D92a7a57D4150Ee08aaf3423",
          "name": "SLC",
          "symbol": "SLC",
          "decimals": 18,
          "icon": "http://testapi.artixv.com/coin/SLC-logo.png",
          "amount": "999999999999999955815",
          "totalPrice": 0
        },
        "tokenB": {
          "address": "0x653d07E59d7FEb93F0c0199a12dA6730845D6a68",
          "name": "USDC",
          "symbol": "USDC",
          "decimals": 18,
          "icon": "http://testapi.artixv.com/coin/usdc-logo.png",
          "amount": "1000000000000000000000",
          "totalPrice": 0
        },
        "time": "1719896281"
      },
      {
        "type": "Add",
        "pairToken": {
          "address": "0x391CB85Bb82059C0B3bEaf2B3BaD2b9A21E43F23",
          "name": "USDC&SLC LP",
          "symbol": "USDC&SLC LP",
          "decimals": 18,
          "icon": "",
          "amount": "0",
          "totalPrice": 0
        },
        "tokenA": {
          "address": "0x84A1894b366a2346D92a7a57D4150Ee08aaf3423",
          "name": "SLC",
          "symbol": "SLC",
          "decimals": 18,
          "icon": "http://testapi.artixv.com/coin/SLC-logo.png",
          "amount": "1000000000000000000000",
          "totalPrice": 0
        },
        "tokenB": {
          "address": "0x653d07E59d7FEb93F0c0199a12dA6730845D6a68",
          "name": "USDC",
          "symbol": "USDC",
          "decimals": 18,
          "icon": "http://testapi.artixv.com/coin/usdc-logo.png",
          "amount": "1000000000000000000000",
          "totalPrice": 0
        },
        "time": "1719896255"
      },
      {
        "type": "Add",
        "pairToken": {
          "address": "0xe5Af1d4d7195F9f582D12C43BD400EE9d251FA9e",
          "name": "BTC&SLC LP",
          "symbol": "BTC&SLC LP",
          "decimals": 18,
          "icon": "",
          "amount": "11117546643567455846",
          "totalPrice": 0
        },
        "tokenA": {
          "address": "0x84A1894b366a2346D92a7a57D4150Ee08aaf3423",
          "name": "SLC",
          "symbol": "SLC",
          "decimals": 18,
          "icon": "http://testapi.artixv.com/coin/SLC-logo.png",
          "amount": "10000000000000000000",
          "totalPrice": 0
        },
        "tokenB": {
          "address": "0x7CBf5971d740b9f8eB957D8b3a07617fCd2AF36E",
          "name": "BTC",
          "symbol": "BTC",
          "decimals": 18,
          "icon": "http://testapi.artixv.com/coin/bitcoin-logo.png",
          "amount": "247227366457541",
          "totalPrice": 0
        },
        "time": "1719821509"
      },
      {
        "type": "Swap",
        "pay": {
          "token": {
            "address": "0x16C2473A9957d00B832C27cFa34773721f47992e",
            "name": "WXCFX",
            "symbol": "WXCFX",
            "decimals": 18,
            "icon": "http://testapi.artixv.com/coin/wxCFX-logo.png"
          },
          "amount": "100000000000000000000"
        },
        "received": {
          "token": {
            "address": "0x84A1894b366a2346D92a7a57D4150Ee08aaf3423",
            "name": "SLC",
            "symbol": "SLC",
            "decimals": 18,
            "icon": "http://testapi.artixv.com/coin/wxCFX-logo.png"
          },
          "amount": "23202888362063668337"
        },
        "time": "1719821387"
      },
      {
        "type": "Add",
        "pairToken": {
          "address": "0x453f3dcE4Ae790d45e1B660bE384Cf77C12E14F3",
          "name": "WXCFX&SLC LP",
          "symbol": "WXCFX&SLC LP",
          "decimals": 18,
          "icon": "",
          "amount": "246189202780699194",
          "totalPrice": 0
        },
        "tokenA": {
          "address": "0x84A1894b366a2346D92a7a57D4150Ee08aaf3423",
          "name": "SLC",
          "symbol": "SLC",
          "decimals": 18,
          "icon": "http://testapi.artixv.com/coin/SLC-logo.png",
          "amount": "242440709157284255",
          "totalPrice": 0
        },
        "tokenB": {
          "address": "0x16C2473A9957d00B832C27cFa34773721f47992e",
          "name": "WXCFX",
          "symbol": "WXCFX",
          "decimals": 18,
          "icon": "http://testapi.artixv.com/coin/wxCFX-logo.png",
          "amount": "1000000000000000000",
          "totalPrice": 0
        },
        "time": "1719489081"
      }
    ]
  }
}